gds2palace/__init__.py
gds2palace/util_elmer.py
gds2palace/util_gds_reader.py
gds2palace/util_simulation_setup.py
gds2palace/util_stackup_reader.py
gds2palace/util_utilities.py
gds2palace-0.1.17.dist-info/licenses/LICENSE
gds2palace-0.1.17.dist-info/METADATA
gds2palace-0.1.17.dist-info/WHEEL
gds2palace-0.1.17.dist-info/top_level.txt
gds2palace-0.1.17.dist-info/RECORD
