Metadata-Version: 2.4
Name: gds2palace
Version: 0.1.17
Summary: Create AWS Palace model from RFIC GDSII layout file
Author-email: Volker Muehlhaus <volker@muehlhaus.com>
License: Apache
Requires-Python: >=3.6
License-File: LICENSE
Requires-Dist: gdspy>1.6.0
Requires-Dist: gmsh
Requires-Dist: scikit-rf
Requires-Dist: matplotlib
Requires-Dist: PySide6
Dynamic: license-file
